Metadata-Version: 1.1
Name: libpythonpro-gesli
Version: 0.2
Summary: Este é apenas um teste com o Módulo para exemplificar construção de projetos Python no curso PyTools
Home-page: https://github.com/Gesli/libpythonpro
Author: Gesli Medina de Avelar
Author-email: gesli.medina@gmail.com
License: GNU AFFERO GENERAL PUBLIC LICENSE
Platform: UNKNOWN
Classifier: Development Status :: 2 - Pre-Alpha
Classifier: Environment :: Console
Classifier: Intended Audience :: Developers
Classifier: License :: OSI Approved :: GNU Affero General Public License v3 or later (AGPLv3+)
Classifier: Operating System :: OS Independent
Classifier: Programming Language :: Python
Classifier: Programming Language :: Python :: 3.6
Classifier: Framework :: Pytest
